Metadata-Version: 2.1
Name: marsa
Version: 1.0.0
Summary: A Python library that lets you experiment with the mathematics of the Rivest–Shamir–Adleman (RSA) cryptosystem.
Home-page: https://github.com/jpvitan/marsa
Author: Justine Paul Vitan
Author-email: justinepaulvitan5@gmail.com
Classifier: Programming Language :: Python :: 3
Classifier: License :: OSI Approved :: MIT License
Classifier: Operating System :: OS Independent
Requires-Python: >=3.6
License-File: LICENSE
